wildnlp/__init__.py
wildnlp/aspects/__init__.py
wildnlp/aspects/add_sub_string.py
wildnlp/aspects/articles.py
wildnlp/aspects/base.py
wildnlp/aspects/change_char.py
wildnlp/aspects/digits2words.py
wildnlp/aspects/misspelling.py
wildnlp/aspects/punctuation.py
wildnlp/aspects/qwerty.py
wildnlp/aspects/remove_char.py
wildnlp/aspects/sentiment_masking.py
wildnlp/aspects/swap.py
wildnlp/aspects/utils.py
wildnlp/aspects/white_spaces.py
wildnlp/aspects/auxiliary/homophones.json
wildnlp/aspects/auxiliary/misspellings.json
wildnlp/aspects/auxiliary/negative_words.txt
wildnlp/aspects/auxiliary/ocr.json
wildnlp/aspects/auxiliary/ocr_pl.json
wildnlp/aspects/auxiliary/positive_words.txt
wildnlp/aspects/auxiliary/qwerty.json
wildnlp/aspects/dummy/__init__.py
wildnlp/aspects/dummy/piglatin.py
wildnlp/aspects/dummy/reverser.py
wildnlp/datasets/__init__.py
wildnlp/datasets/base.py
wildnlp/datasets/conll.py
wildnlp/datasets/imdb.py
wildnlp/datasets/sample_dataset.py
wildnlp/datasets/snli.py
wildnlp/datasets/squad.py
wild_nlp-1.0.2.dist-info/METADATA
wild_nlp-1.0.2.dist-info/WHEEL
wild_nlp-1.0.2.dist-info/top_level.txt
wild_nlp-1.0.2.dist-info/RECORD
