Metadata-Version: 2.1
Name: wild-nlp
Version: 1.0.2
Summary: Text aspects for nlp models
Home-page: https://github.com/MI2DataLab/WildNLP
Author: Dominika Basaj, Barbara Rychalska, Alicja Gosiewska, Adam Słucki
Author-email: adam.slucki@gmail.com
License: BSD
Platform: UNKNOWN
Classifier: Development Status :: 4 - Beta
Classifier: Topic :: Text Processing
Classifier: License :: OSI Approved :: BSD License
Requires-Dist: numpy
Requires-Dist: num2words
